pr_creator/__init__.py
pr_creator/__main__.py
pr_creator/main.py
pr_creator/tickets/__init__.py
pr_creator/tickets/branches.py
pr_creator/tickets/check_autocomplete.py
pr_creator/tickets/completer.py
pr_creator/tickets/constants.py
pr_creator/tickets/jira.py
pr_creator/tickets/password.py
pr_creator/tickets/settings.py
pr_creator/tickets/tests.py
pr_creator/tickets/github/__init__.py
pr_creator/tickets/github/api.py
pr_creator/tickets/github/tests.py
pr_creator-0.0.9.dist-info/DESCRIPTION.rst
pr_creator-0.0.9.dist-info/METADATA
pr_creator-0.0.9.dist-info/RECORD
pr_creator-0.0.9.dist-info/WHEEL
pr_creator-0.0.9.dist-info/entry_points.txt
pr_creator-0.0.9.dist-info/metadata.json
pr_creator-0.0.9.dist-info/top_level.txt
