Metadata-Version: 2.0
Name: pr-creator
Version: 0.0.9
Summary: Git lifestyle utility for NaviGuide
Home-page: https://github.com/bwarren2/create-prs
Author: Ben Warren
Author-email: bwarren@eab.com
License: BSD
Keywords: happy dev
Platform: UNKNOWN
Classifier: Topic :: Utilities
Classifier: License :: OSI Approved :: BSD License
Requires-Dist: requests (>=2.18.4)
